gbintk/__init__.py
gbintk/cli.py
gbintk/support/__init__.py
gbintk/support/evaluate.py
gbintk/support/prep_result.py
gbintk/support/visualise_result_Flye.py
gbintk/support/visualise_result_MEGAHIT.py
gbintk/support/visualise_result_SPAdes.py
gbintk-1.0.3.dist-info/entry_points.txt
gbintk-1.0.3.dist-info/licenses/LICENSE
gbintk-1.0.3.dist-info/WHEEL
gbintk-1.0.3.dist-info/METADATA
gbintk-1.0.3.dist-info/RECORD
