Metadata-Version: 2.4
Name: gbintk
Version: 1.0.3
Summary: gbintk (GraphBin-Tk): Assembly graph-based metagenomic binning toolkit
Keywords: metagenomics,binning,contigs,bioinformatics
Author-email: Vijini Mallawaarachchi <viji.mallawaarachchi@gmail.com>
Requires-Python: >=3.9,<3.13
Classifier: Development Status :: 5 - Production/Stable
Classifier: Intended Audience :: Science/Research
Classifier: License :: OSI Approved :: GNU General Public License v3 or later (GPLv3+)
Classifier: Topic :: Scientific/Engineering :: Bio-Informatics
Classifier: Operating System :: MacOS
Classifier: Operating System :: POSIX
Classifier: Programming Language :: Python :: 3
License-File: LICENSE
Requires-Dist: click
Requires-Dist: cogent3
Requires-Dist: igraph
Requires-Dist: cairocffi
Requires-Dist: pycairo
Requires-Dist: networkx
Requires-Dist: scipy
Requires-Dist: numpy
Requires-Dist: pandas
Requires-Dist: tqdm
Requires-Dist: tabulate
Requires-Dist: graphbin
Requires-Dist: graphbin2>=1.3.3
Requires-Dist: metacoag>=1.2.1
Requires-Dist: black ; extra == "dev"
Requires-Dist: click ; extra == "dev"
Requires-Dist: flit ; extra == "dev"
Requires-Dist: isort==5.13.2 ; extra == "dev"
Requires-Dist: gbintk[test] ; extra == "dev"
Requires-Dist: pytest ; extra == "test"
Requires-Dist: pytest-cov ; extra == "test"
Requires-Dist: pytest-xdist ; extra == "test"
Requires-Dist: pillow>10,<11 ; extra == "test"
Provides-Extra: dev
Provides-Extra: test
